exponential/__init__.py
exponential/__main__.py
exponential/alembic/env.py
exponential/alembic/README
exponential/alembic/script.py.mako
exponential/alembic/versions/260dbcc8b680_adds_tables.py
exponential/alembic/versions/67cc006d50bf_add_profile_image_column.py
exponential/alembic/versions/eb5866d51fd2_change_columns_to_be_nullable.py
exponential/alembic.ini
exponential/api/__init__.py
exponential/api/router.py
exponential/api/utils.py
exponential/api/v1/__init__.py
exponential/api/v1/api_key.py
exponential/api/v1/base.py
exponential/api/v1/callback.py
exponential/api/v1/chat.py
exponential/api/v1/components.py
exponential/api/v1/endpoints.py
exponential/api/v1/flows.py
exponential/api/v1/login.py
exponential/api/v1/schemas.py
exponential/api/v1/users.py
exponential/api/v1/validate.py
exponential/components/__init__.py
exponential/components/agents/__init__.py
exponential/components/agents/OpenAIConversationalAgent.py
exponential/components/chains/__init__.py
exponential/components/chains/PromptRunner.py
exponential/components/llms/__init__.py
exponential/components/llms/HuggingFaceEndpoints.py
exponential/components/retrievers/__init__.py
exponential/components/retrievers/MetalRetriever.py
exponential/components/textsplitters/__init__.py
exponential/components/textsplitters/LanguageRecursiveTextSplitter.py
exponential/components/textsplitters/RecursiveCharacterTextSplitter.py
exponential/components/toolkits/__init__.py
exponential/components/toolkits/Metaphor.py
exponential/components/utilities/GetRequest.py
exponential/components/utilities/JSONDocumentBuilder.py
exponential/components/utilities/PostRequest.py
exponential/components/utilities/UpdateRequest.py
exponential/components/vectorstores/__init__.py
exponential/components/vectorstores/Chroma.py
exponential/components/vectorstores/Vectara.py
exponential/config.yaml
exponential/core/__init__.py
exponential/core/celery_app.py
exponential/core/celeryconfig.py
exponential/custom/__init__.py
exponential-0.5.3.dist-info/entry_points.txt
exponential-0.5.3.dist-info/LICENSE
exponential-0.5.3.dist-info/METADATA
exponential-0.5.3.dist-info/WHEEL
exponential-0.5.3.dist-info/RECORD
