Metadata-Version: 2.1
Name: exponential
Version: 0.5.3
Summary: A Python package with a built-in web application
Home-page: https://github.com/ridabourji1988/Exponential-ai
License: MIT
Keywords: nlp,langchain,openai,gpt,gui
Author: Reda Bourji
Maintainer: Reda Bourji
Maintainer-email: RedaBourji@gmail.com
Requires-Python: >=3.9,<3.11
Classifier: License :: OSI Approved :: MIT License
Classifier: Programming Language :: Python :: 3
Classifier: Programming Language :: Python :: 3.9
Classifier: Programming Language :: Python :: 3.10
Provides-Extra: all
Provides-Extra: deploy
Provides-Extra: local
Requires-Dist: alembic (>=1.12.0,<2.0.0)
Requires-Dist: anthropic (>=0.3.0,<0.4.0)
Requires-Dist: appdirs (>=1.4.4,<2.0.0)
Requires-Dist: bcrypt (>=4.0.1,<5.0.0)
Requires-Dist: beautifulsoup4 (>=4.12.2,<5.0.0)
Requires-Dist: cachetools (>=5.3.1,<6.0.0)
Requires-Dist: celery[redis] (>=5.3.1,<6.0.0) ; extra == "deploy"
Requires-Dist: certifi (>=2023.5.7,<2024.0.0)
Requires-Dist: chromadb (>=0.3.21,<0.4.0)
Requires-Dist: cohere (>=4.27.0,<5.0.0)
Requires-Dist: ctransformers (>=0.2.10,<0.3.0) ; extra == "local"
Requires-Dist: docstring-parser (>=0.15,<0.16)
Requires-Dist: faiss-cpu (>=1.7.4,<2.0.0)
Requires-Dist: fake-useragent (>=1.2.1,<2.0.0)
Requires-Dist: fastapi (>=0.103.0,<0.104.0)
Requires-Dist: fastavro (>=1.8.0,<2.0.0)
Requires-Dist: flower (>=2.0.0,<3.0.0) ; extra == "deploy"
Requires-Dist: google-api-python-client (>=2.79.0,<3.0.0)
Requires-Dist: google-cloud-aiplatform (>=1.26.1,<2.0.0)
Requires-Dist: google-search-results (>=2.4.1,<3.0.0)
Requires-Dist: gunicorn (>=21.2.0,<22.0.0)
Requires-Dist: huggingface-hub[inference] (>=0.16.0,<0.17.0)
Requires-Dist: jina (==3.15.2)
Requires-Dist: langchain (>=0.0.308,<0.0.309)
Requires-Dist: langchain-experimental (>=0.0.8,<0.0.9)
Requires-Dist: langfuse (>=1.0.13,<2.0.0)
Requires-Dist: llama-cpp-python (>=0.1.0,<0.2.0) ; extra == "local"
Requires-Dist: loguru (>=0.7.1,<0.8.0)
Requires-Dist: lxml (>=4.9.2,<5.0.0)
Requires-Dist: markupsafe (>=2.1.3,<3.0.0)
Requires-Dist: metal-sdk (>=2.2.0,<3.0.0)
Requires-Dist: metaphor-python (>=0.1.11,<0.2.0)
Requires-Dist: multiprocess (>=0.70.14,<0.71.0)
Requires-Dist: networkx (>=3.1,<4.0)
Requires-Dist: openai (>=0.27.8,<0.28.0)
Requires-Dist: orjson (==3.9.3)
Requires-Dist: pandas (==2.0.3)
Requires-Dist: passlib (>=1.7.4,<2.0.0)
Requires-Dist: pillow (>=10.0.0,<11.0.0)
Requires-Dist: pinecone-client (>=2.2.2,<3.0.0)
Requires-Dist: psycopg (>=3.1.9,<4.0.0)
Requires-Dist: psycopg-binary (>=3.1.9,<4.0.0)
Requires-Dist: psycopg2-binary (>=2.9.6,<3.0.0)
Requires-Dist: pyarrow (>=12.0.0,<13.0.0)
Requires-Dist: pymongo (>=4.4.0,<5.0.0)
Requires-Dist: pypdf (>=3.15.0,<4.0.0)
Requires-Dist: pysrt (>=1.1.2,<2.0.0)
Requires-Dist: python-jose (>=3.3.0,<4.0.0)
Requires-Dist: python-multipart (>=0.0.6,<0.0.7)
Requires-Dist: pywin32 (>=306,<307) ; sys_platform == "win32"
Requires-Dist: qdrant-client (>=1.4.0,<2.0.0)
Requires-Dist: redis (>=4.6.0,<5.0.0) ; extra == "deploy"
Requires-Dist: rich (>=13.5.0,<14.0.0)
Requires-Dist: sentence-transformers (>=2.2.2,<3.0.0) ; extra == "local"
Requires-Dist: sqlmodel (>=0.0.8,<0.0.9)
Requires-Dist: supabase (>=1.0.3,<2.0.0)
Requires-Dist: tiktoken (>=0.5.0,<0.6.0)
Requires-Dist: typer (>=0.9.0,<0.10.0)
Requires-Dist: types-cachetools (>=5.3.0.5,<6.0.0.0)
Requires-Dist: unstructured (>=0.10.0,<0.11.0)
Requires-Dist: uvicorn (>=0.23.0,<0.24.0)
Requires-Dist: weaviate-client (>=3.23.0,<4.0.0)
Requires-Dist: websockets (>=10.3,<11.0)
Requires-Dist: wikipedia (>=1.4.0,<2.0.0)
Project-URL: Documentation, https://docs.exponential.org
Project-URL: Repository, https://github.com/ridabourji1988/Exponential-ai
